Metadata-Version: 2.1
Name: fakeua
Version: 0.1.2
Summary: Python3 module made as a wrapper of fake-useragent.
Home-page: https://github.com/carlosplanchon/fakeua
Author: Carlos A. Planchón
Author-email: bubbledoloresuruguay2@gmail.com
License: GPL3
Download-URL: https://github.com/carlosplanchon/fakeua/archive/v0.1.2.tar.gz
Keywords: fake,useragent,networking,web
Platform: UNKNOWN
Classifier: Intended Audience :: Developers
Classifier: Topic :: Software Development :: Build Tools
Classifier: License :: OSI Approved :: GNU General Public License v3 (GPLv3)
Classifier: Programming Language :: Python :: 3
Classifier: Programming Language :: Python :: 3.4
Classifier: Programming Language :: Python :: 3.5
Classifier: Programming Language :: Python :: 3.6
Classifier: Programming Language :: Python :: 3.7
